{
  "law_name": "The Pakistan Environmental Protection Act",
  "year": 1997,
  "chapters": [
    {
      "chapter_title": "Contents",
      "sections": [
        {
          "section_no": "1",
          "section_title": "Short title, extent and commencement",
          "body": "(1) This Act may be called the Pakistan Environmental Protection Act, 1997. (2) It extends to the whole of Pakistan. (3) It shall come into force at once."
        },
        {
          "section_no": "2",
          "section_title": "Definitions",
          "body": "In this Act, unless there is anything repugnant in the subject or context, various definitions are provided for terms such as 'adverse environmental effect', 'agricultural waste', 'air pollutant', 'biodiversity', 'Council', 'discharge', 'ecosystem', 'effluent', 'emission standards', 'environment', 'environmental impact assessment', 'Environmental Magistrate', 'Environmental Tribunal', 'Exclusive Economic Zone', 'factory', 'Federal Agency', 'Government Agency', 'hazardous substance', 'hazardous waste', 'historic waters', 'hospital waste', 'industrial activity', 'industrial waste', 'initial environmental examination', 'local authority', 'local council', 'motor vehicle', 'municipal waste', 'National Environmental Quality Standards', 'noise', 'nuclear waste', 'person', 'pollution', 'prescribed', 'project', 'proponent', 'Provincial Agency', 'regulations', 'rules', 'sewage', and 'standards'."
        },
        {
          "section_no": "3",
          "section_title": "Establishment of the Pakistan Environmental Protection Council",
          "body": ""
        },
        {
          "section_no": "4",
          "section_title": "Functions and powers of the Council",
          "body": ""
        },
        {
          "section_no": "5",
          "section_title": "Establishment of the Pakistan Environmental Protection Agency",
          "body": ""
        },
        {
          "section_no": "6",
          "section_title": "Functions of the Federal Agency",
          "body": ""
        },
        {
          "section_no": "7",
          "section_title": "Powers of the Federal Agency",
          "body": ""
        },
        {
          "section_no": "8",
          "section_title": "Establishment, powers and functions of the Provincial Environmental Protection Agencies",
          "body": ""
        },
        {
          "section_no": "9",
          "section_title": "Establishment of the Provincial Sustainable Development Funds",
          "body": ""
        },
        {
          "section_no": "10",
          "section_title": "Management of the Provincial Sustainable Development Fund",
          "body": ""
        },
        {
          "section_no": "11",
          "section_title": "Prohibition of certain discharges or emissions",
          "body": ""
        },
        {
          "section_no": "12",
          "section_title": "Initial environmental examination and environmental impact assessment",
          "body": ""
        },
        {
          "section_no": "13",
          "section_title": "Prohibition of import of hazardous waste",
          "body": ""
        },
        {
          "section_no": "14",
          "section_title": "Handling of hazardous substances",
          "body": ""
        },
        {
          "section_no": "15",
          "section_title": "Regulation of motor vehicles",
          "body": ""
        },
        {
          "section_no": "16",
          "section_title": "Environmental protection order",
          "body": ""
        },
        {
          "section_no": "17",
          "section_title": "Penalties",
          "body": ""
        },
        {
          "section_no": "18",
          "section_title": "Offences by bodies corporate",
          "body": ""
        },
        {
          "section_no": "19",
          "section_title": "Offences by Government Agencies, local authorities or local councils",
          "body": ""
        },
        {
          "section_no": "20",
          "section_title": "Environmental Tribunals",
          "body": ""
        },
        {
          "section_no": "21",
          "section_title": "Jurisdiction and powers of Environmental Tribunals",
          "body": ""
        },
        {
          "section_no": "22",
          "section_title": "Appeals to the Environmental Tribunal",
          "body": ""
        },
        {
          "section_no": "23",
          "section_title": "Appeals from orders of the Environmental Tribunal",
          "body": ""
        },
        {
          "section_no": "24",
          "section_title": "Jurisdiction of Environmental Magistrates",
          "body": ""
        },
        {
          "section_no": "25",
          "section_title": "Appeals from orders of Environmental Magistrates",
          "body": ""
        },
        {
          "section_no": "26",
          "section_title": "Power to delegate",
          "body": ""
        },
        {
          "section_no": "27",
          "section_title": "Power to give directions",
          "body": ""
        },
        {
          "section_no": "28",
          "section_title": "Indemnity",
          "body": ""
        },
        {
          "section_no": "29",
          "section_title": "Dues recoverable as arrears of land revenue",
          "body": ""
        },
        {
          "section_no": "30",
          "section_title": "Act to override other laws",
          "body": ""
        },
        {
          "section_no": "31",
          "section_title": "Power to make rules",
          "body": ""
        },
        {
          "section_no": "32",
          "section_title": "Power to amend the Schedule",
          "body": ""
        },
        {
          "section_no": "33",
          "section_title": "Power to make regulations",
          "body": ""
        },
        {
          "section_no": "34",
          "section_title": "Repeal, savings and succession",
          "body": ""
        }
      ]
    }
  ],
  "source_file": "administrator17094efb999f9a865461eb1498175947.txt"
}